data_scripts/__init__.py
data_scripts/init__.py
data_scripts/local/__init__.py
data_scripts/local/utils.py
data_scripts-0.1.1.dist-info/LICENSE
data_scripts-0.1.1.dist-info/METADATA
data_scripts-0.1.1.dist-info/WHEEL
data_scripts-0.1.1.dist-info/entry_points.txt
data_scripts-0.1.1.dist-info/top_level.txt
data_scripts-0.1.1.dist-info/RECORD
