Metadata-Version: 2.1
Name: data-scripts
Version: 0.1.1
Summary: Scripts for managing massive amounts of Data
Home-page: https://github.com/jbcurtin/data_scripts
Author: Joseph Curtin <42@jbcurtin.io
Author-email: data-scripts@jbcurtin.io
License: MIT
Platform: UNKNOWN
Classifier: Operating System :: OS Independent
Classifier: Programming Language :: Python
Classifier: Programming Language :: Python :: 3
Classifier: Programming Language :: Python :: 3.6
Classifier: Programming Language :: Python :: 3.7
Classifier: Programming Language :: Python :: 3 :: Only
Requires-Python: >=3.6
